LICENSE
MANIFEST.in
README.rst
setup.cfg
setup.py
docs/Makefile
docs/changelog.rst
docs/conf.py
docs/index.rst
docs/make.bat
docs/usage.rst
examples/using_selenium.py
requirements/docs.txt
requirements/test.txt
serlist/__init__.py
serlist/scraper.py
serlist/selector.py
serlist.egg-info/PKG-INFO
serlist.egg-info/SOURCES.txt
serlist.egg-info/dependency_links.txt
serlist.egg-info/not-zip-safe
serlist.egg-info/requires.txt
serlist.egg-info/top_level.txt
tests/__init__.py
tests/test_selector.py