Metadata-Version: 1.2
Name: serlist
Version: 0.1.1
Summary: Search engine results page scraper
Home-page: https://github.com/jadbin/serlist
Author: jadbin
Author-email: jadbin.com@hotmail.com
License: Apache 2
Platform: UNKNOWN
Classifier: License :: OSI Approved :: Apache Software License
Classifier: Intended Audience :: Developers
Classifier: Programming Language :: Python
Classifier: Programming Language :: Python :: 3
Classifier: Programming Language :: Python :: 3.5
Classifier: Programming Language :: Python :: 3.6
Classifier: Topic :: Software Development :: Libraries :: Python Modules
Requires-Python: >=3.5
